LICENSE
MANIFEST.in
README.md
setup.py
visualize/__init__.py
visualize.egg-info/PKG-INFO
visualize.egg-info/SOURCES.txt
visualize.egg-info/dependency_links.txt
visualize.egg-info/requires.txt
visualize.egg-info/top_level.txt
visualize/example/__init__.py
visualize/example/grid_attention_example.py
visualize/example/region_attention_example.py
visualize/grid_attention_visualization/__init__.py
visualize/grid_attention_visualization/visualize_attention_map.py
visualize/grid_attention_visualization/visualize_attention_map_V2.py
visualize/line_chart/__init__.py
visualize/line_chart/drawer.py
visualize/line_chart/test.py
visualize/region_attention_visualization/__init__.py
visualize/region_attention_visualization/visualize_region_attention_map.py
visualize/test_data/__init__.py
visualize/test_data/example.jpg