Metadata-Version: 2.1
Name: visualize
Version: 0.5.1
Summary: useful visualization function
Home-page: https://github.com/rentainhe/visualization
Author: rentianhe
Author-email: 596106517@qq.com
License: MIT
Keywords: computer vision
Platform: any
Classifier: License :: OSI Approved :: MIT License
Classifier: Programming Language :: Python :: 3
Classifier: Programming Language :: Python :: 3.5
Classifier: Programming Language :: Python :: 3.6
Classifier: Programming Language :: Python :: 3.7
Classifier: Programming Language :: Python :: 3.8
Classifier: Programming Language :: Python :: 3.9
Classifier: Intended Audience :: Developers
Classifier: Operating System :: OS Independent
License-File: LICENSE
